cachetoolz/__init__.py
cachetoolz/decorator.py
cachetoolz/exceptions.py
cachetoolz/log.py
cachetoolz/types.py
cachetoolz/utils.py
cachetoolz/abc/__init__.py
cachetoolz/abc/backend.py
cachetoolz/abc/coder.py
cachetoolz/abc/serializer.py
cachetoolz/backend/__init__.py
cachetoolz/backend/inmemory.py
cachetoolz/backend/mongo.py
cachetoolz/backend/redis.py
cachetoolz/coder/__init__.py
cachetoolz/coder/decoder.py
cachetoolz/coder/encoder.py
cachetoolz-0.4.1.dist-info/METADATA
cachetoolz-0.4.1.dist-info/WHEEL
cachetoolz-0.4.1.dist-info/licenses/LICENSE
cachetoolz-0.4.1.dist-info/RECORD
