Metadata-Version: 2.3
Name: cachetoolz
Version: 0.4.1
Summary: This library provides a decorator for caching functions
Project-URL: Homepage, https://codeberg.org/taconi/cachetoolz/#cache-toolz
Project-URL: Changelog, https://cachetoolz.readthedocs.io/changelog
Project-URL: Contributing, https://cachetoolz.readthedocs.io/contributing
Project-URL: Documentation, https://cachetoolz.readthedocs.io
Project-URL: Issue Tracker, https://codeberg.org/taconi/cachetoolz/issues
Project-URL: Repository, https://codeberg.org/taconi/cachetoolz/
Author-email: taconi <igor.taconi@protonmail.com>
Maintainer-email: taconi <igor.taconi@protonmail.com>
License-Expression: GPL-3.0-or-later
License-File: LICENSE
Keywords: async,cache,mongo,python,redis
Classifier: Development Status :: 4 - Beta
Classifier: License :: OSI Approved :: GNU General Public License v3 or later (GPLv3+)
Classifier: Operating System :: OS Independent
Classifier: Programming Language :: Python :: 3.9
Classifier: Programming Language :: Python :: 3.10
Classifier: Programming Language :: Python :: 3.11
Classifier: Programming Language :: Python :: 3.12
Classifier: Programming Language :: Python :: 3.13
Classifier: Programming Language :: Python :: Implementation :: CPython
Classifier: Topic :: Utilities
Requires-Python: >=3.9
Requires-Dist: charset-normalizer>=3.2.0
Requires-Dist: funcy>=2.0
Requires-Dist: get-annotations>=0.1.2; python_version < '3.10'
Requires-Dist: nest-asyncio>=1.5.6
Requires-Dist: typing-extensions>=4.7.1; python_version < '3.10'
Provides-Extra: mongo
Requires-Dist: motor>=3.3.2; extra == 'mongo'
Requires-Dist: pymongo>=4.6.2; extra == 'mongo'
Provides-Extra: redis
Requires-Dist: redis>=5.0.1; extra == 'redis'
